0,nop,nop
1,aconst_null,aconstNull
2,iconst_m1,iconstM1
3,iconst_0,iconst0
4,iconst_1,iconst1
5,iconst_2,iconst2
6,iconst_3,iconst3
7,iconst_4,iconst4
8,iconst_5,iconst5
9,lconst_0,lconst0
10,lconst_1,lconst1
11,fconst_0,fconst0
12,fconst_1,fconst1
13,fconst_2,fconst2
14,dconst_0,dconst0
15,dconst_1,dconst1
16,bipush,bipush
17,sipush,sipush
18,ldc,ldc
19,ldc_w,ldc
20,ldc2_w,ldc2
21,iload,iload
22,lload,lload
23,fload,fload
24,dload,dload
25,aload,aload
26,iload_0,iload
27,iload_1,iload
28,iload_2,iload
29,iload_3,iload
30,lload_0,lload
31,lload_1,lload
32,lload_2,lload
33,lload_3,lload
34,fload_0,fload
35,fload_1,fload
36,fload_2,fload
37,fload_3,fload
38,dload_0,dload
39,dload_1,dload
40,dload_2,dload
41,dload_3,dload
42,aload_0,aload
43,aload_1,aload
44,aload_2,aload
45,aload_3,aload
46,iaload,iaload
47,laload,laload
48,faload,faload
49,daload,daload
50,aaload,aaload
51,baload,baload
52,caload,caload
53,saload,saload
54,istore,istore
55,lstore,lstore
56,fstore,fstore
57,dstore,dstore
58,astore,astore
59,istore_0,istore
60,istore_1,istore
61,istore_2,istore
62,istore_3,istore
63,lstore_0,lstore
64,lstore_1,lstore
65,lstore_2,lstore
66,lstore_3,lstore
67,fstore_0,fstore
68,fstore_1,fstore
69,fstore_2,fstore
70,fstore_3,fstore
71,dstore_0,dstore
72,dstore_1,dstore
73,dstore_2,dstore
74,dstore_3,dstore
75,astore_0,astore
76,astore_1,astore
77,astore_2,astore
78,astore_3,astore
79,iastore,iastore
80,lastore,lastore
81,fastore,fastore
82,dastore,dastore
83,aastore,aastore
84,bastore,bastore
85,castore,castore
86,sastore,sastore
87,pop,pop
88,pop2,pop2
89,dup,dup
90,dup_x1,dupX1
91,dup_x2,dupX2
92,dup2,dup2
93,dup2_x1,dup2X1
94,dup2_x2,dup2X2
95,swap,swap
96,iadd,iadd
97,ladd,ladd
98,fadd,fadd
99,dadd,dadd
100,isub,isub
101,lsub,lsub
102,fsub,fsub
103,dsub,dsub
104,imul,imul
105,lmul,lmul
106,fmul,fmul
107,dmul,dmul
108,idiv,idiv
109,ldiv,ldiv
110,fdiv,fdiv
111,ddiv,ddiv
112,irem,irem
113,lrem,lrem
114,frem,frem
115,drem,drem
116,ineg,ineg
117,lneg,lneg
118,fneg,fneg
119,dneg,dneg
120,ishl,ishl
121,lshl,lshl
122,ishr,ishr
123,lshr,lshr
124,iushr,iushr
125,lushr,lushr
126,iand,iand
127,land,land
128,ior,ior
129,lor,lor
130,ixor,ixor
131,lxor,lxor
132,iinc,iinc
133,i2l,i2l
134,i2f,i2f
135,i2d,i2d
136,l2i,l2i
137,l2f,l2f
138,l2d,l2d
139,f2i,f2i
140,f2l,f2l
141,f2d,f2d
142,d2i,d2i
143,d2l,d2l
144,d2f,d2f
145,i2b,i2b
146,i2c,i2c
147,i2s,i2s
148,lcmp,lcmp
149,fcmpl,fcmpl
150,fcmpg,fcmpg
151,dcmpl,dcmpl
152,dcmpg,dcmpg
153,ifeq,ifeq
154,ifne,ifne
155,iflt,iflt
156,ifge,ifge
157,ifgt,ifgt
158,ifle,ifle
159,if_icmpeq,ifIcmpeq
160,if_icmpne,ifIcmpne
161,if_icmplt,ifIcmplt
162,if_icmpge,ifIcmpge
163,if_icmpgt,ifIcmpgt
164,if_icmple,ifIcmple
165,if_acmpeq,ifAcmpeq
166,if_acmpne,ifAcmpne
167,goto,gotoInsn
168,jsr,jsr
169,ret,ret
170,tableswitch,tableswitch
171,lookupswitch,lookupswitch
172,ireturn,ireturn
173,lreturn,lreturn
174,freturn,freturn
175,dreturn,dreturn
176,areturn,areturn
177,return,returnInsn
178,getstatic,getstatic
179,putstatic,putstatic
180,getfield,getfield
181,putfield,putfield
182,invokevirtual,invokevirtual
183,invokespecial,invokespecial
184,invokestatic,invokestatic
185,invokeinterface,invokeinterface
186,__unused,noMethod
187,new,newInsn
188,newarray,newarray
189,anewarray,anewarray
190,arraylength,arraylength
191,athrow,athrow
192,checkcast,checkcast
193,instanceof,instanceofInsn
194,monitorenter,monitorenter
195,monitorexit,monitorexit
196,wide,noMethod
197,multianewarray,multianewarray
198,ifnull,ifnull
199,ifnonnull,ifnonnull
200,goto_w,goto
201,jsr_w,jsr
202,breakpoint,breakpoint
203,ldc_quick,ldc
204,__unused,noMethod
205,ldc2_w_quick,ldc2
206,getfield_quick,getfield
207,putfield_quick,putfield
208,getfield2_quick,getfield2
209,putfield2_quick,putfield2
210,__unused,noMethod
211,putstatic_quick,putstatic
212,getstatic2_quick,getstatic2
213,putstatic2_quick,putstatic2
214,invokevirtual_quick,invokevirtual
215,invokenonvirtual_quick,invokenonvirtual
216,invokesuper_quick,invokesuper
217,invokestatic_quick,invokestatic
218,invokeinterface_quick,invokeinterface
219,invokevirtualobject_quick,invokevirtualobject
220,__unused,noMethod
221,new_quick,newInsn
222,anewarray_quick,anewarray
223,multianewarray_quick,multianewarray
224,checkcast_quick,checkcast
225,instanceof_quick,instanceof
226,invokevirtual_quick_w,invokevirtual
227,getfield_quick_w,getfield
228,putfield_quick_w,putfield
229,__unused,noMethod
230,__unused,noMethod
231,__unused,noMethod
232,__unused,noMethod
233,__unused,noMethod
234,__unused,noMethod
235,__unused,noMethod
236,__unused,noMethod
237,__unused,noMethod
238,__unused,noMethod
239,__unused,noMethod
240,__unused,noMethod
241,__unused,noMethod
242,__unused,noMethod
243,__unused,noMethod
244,__unused,noMethod
245,__unused,noMethod
246,__unused,noMethod
247,__unused,noMethod
248,__unused,noMethod
249,__unused,noMethod
250,__unused,noMethod
251,__unused,noMethod
252,__unused,noMethod
253,__unused,noMethod
254,impdep1,impdep
255,impdep2,impdep
